best_date_paris/__init__.py
best_date_paris/cli.py
best_date_paris-0.1.1.dist-info/METADATA
best_date_paris-0.1.1.dist-info/WHEEL
best_date_paris-0.1.1.dist-info/entry_points.txt
best_date_paris-0.1.1.dist-info/top_level.txt
best_date_paris-0.1.1.dist-info/RECORD
